Battleship_yousufaa/__init__.py
Battleship_yousufaa/components.py
Battleship_yousufaa/config.py
Battleship_yousufaa/game_engine.py
Battleship_yousufaa/main.py
Battleship_yousufaa/mp_game_engine.py
Battleship_yousufaa-0.0.1.dist-info/LICENSE
Battleship_yousufaa-0.0.1.dist-info/METADATA
Battleship_yousufaa-0.0.1.dist-info/WHEEL
Battleship_yousufaa-0.0.1.dist-info/top_level.txt
Battleship_yousufaa-0.0.1.dist-info/RECORD
