Metadata-Version: 2.1
Name: Battleship_yousufaa
Version: 0.0.1
Summary: A Battleship game using Python and Flask
Author-email: Yousuf Ahmed <yousufaa@outlook.com>
Project-URL: Homepage, https://github.com/yousufaahmed/Battleship
Project-URL: Issues, https://github.com/yousufaahmed/Battleship/issues
Classifier: Programming Language :: Python :: 3
Classifier: License :: OSI Approved :: MIT License
Classifier: Operating System :: OS Independent
Requires-Python: >=3.8
License-File: LICENSE
